{"name":"packages-server","className":"DataModel","filePaths":["default.project.json"],"children":[{"name":"ReplicatedStorage","className":"ReplicatedStorage","children":[{"name":"Packages","className":"Folder","children":[{"name":"_Index","className":"Folder","children":[{"name":"osyrisrblx_t@3.1.1","className":"Folder","children":[{"name":"t","className":"ModuleScript","filePaths":["Packages\\_Index\\osyrisrblx_t@3.1.1\\t\\lib\\init.lua","Packages\\_Index\\osyrisrblx_t@3.1.1\\t\\default.project.json"]}]}]},{"name":"t","className":"ModuleScript","filePaths":["Packages\\t.lua"]}]}]},{"name":"ServerStorage","className":"ServerStorage","children":[{"name":"ServerPackages","className":"Folder"}]}]}